taliabeeio/__init__.py
taliabeeio-0.1.7.dist-info/DESCRIPTION.rst
taliabeeio-0.1.7.dist-info/METADATA
taliabeeio-0.1.7.dist-info/RECORD
taliabeeio-0.1.7.dist-info/WHEEL
taliabeeio-0.1.7.dist-info/metadata.json
taliabeeio-0.1.7.dist-info/top_level.txt
